{
  "garage_id": "sandy_motel_public",
  "name": "Sandy Motel Parking",
  "type": "public",
  "shared": false,
  "location": {
    "vector": {
      "x": 1117.18,
      "y": 2659.2,
      "z": 38.0
    },
    "width": 30.8,
    "length": 50.6,
    "options": {
      "heading": 0,
      "minZ": 37.0,
      "maxZ": 41.0
    }
  },
  "vehicle_types": [
    "land"
  ],
  "parking_spots": [
    {
      "type": "land",
      "size": 2.0,
      "distance": 1.8,
      "heading": 180.0,
      "coords": {
        "x": 1135.0720214844,
        "y": 2647.3811035156,
        "z": 36.997001647949
      }
    },
    {
      "type": "land",
      "size": 2.0,
      "distance": 1.8,
      "heading": 180.0,
      "coords": {
        "x": 1131.3819580078,
        "y": 2647.4169921875,
        "z": 36.997001647949
      }
    },
    {
      "type": "land",
      "size": 2.0,
      "distance": 1.8,
      "heading": 180.0,
      "coords": {
        "x": 1127.6929931641,
        "y": 2647.4541015625,
        "z": 36.995998382568
      }
    },
    {
      "type": "land",
      "size": 2.0,
      "distance": 1.8,
      "heading": 180.0,
      "coords": {
        "x": 1124.0040283203,
        "y": 2647.4899902344,
        "z": 36.995998382568
      }
    },
    {
      "type": "land",
      "size": 2.0,
      "distance": 1.8,
      "heading": 180.0,
      "coords": {
        "x": 1120.3139648438,
        "y": 2647.5270996094,
        "z": 36.995998382568
      }
    },
    {
      "type": "land",
      "size": 2.0,
      "distance": 1.8,
      "heading": 180.0,
      "coords": {
        "x": 1116.625,
        "y": 2647.5639648438,
        "z": 36.995998382568
      }
    },
    {
      "type": "land",
      "size": 2.0,
      "distance": 1.8,
      "heading": 90.0,
      "coords": {
        "x": 1111.6219482422,
        "y": 2654.1640625,
        "z": 36.995998382568
      }
    },
    {
      "type": "land",
      "size": 2.0,
      "distance": 1.8,
      "heading": 90.0,
      "coords": {
        "x": 1111.5350341797,
        "y": 2657.7690429688,
        "z": 36.995998382568
      }
    },
    {
      "type": "land",
      "size": 2.0,
      "distance": 1.8,
      "heading": 180.0,
      "coords": {
        "x": 1105.5209960938,
        "y": 2662.9919433594,
        "z": 36.995998382568
      }
    },
    {
      "type": "land",
      "size": 2.0,
      "distance": 1.8,
      "heading": 180.0,
      "coords": {
        "x": 1101.8520507812,
        "y": 2662.9599609375,
        "z": 36.995998382568
      }
    },
    {
      "type": "land",
      "size": 2.0,
      "distance": 1.8,
      "heading": 180.0,
      "coords": {
        "x": 1098.1820068359,
        "y": 2662.9279785156,
        "z": 36.995998382568
      }
    }
  ]
}